opendors/__init__.py
opendors/abc.py
opendors/cli.py
opendors/exceptions.py
opendors/logging.py
opendors/model.py
opendors/rules/__init__.py
opendors/rules/archive.py
opendors/rules/extract_urls.py
opendors/rules/joss.py
opendors/rules/languages.py
opendors/rules/merge.py
opendors/rules/repository.py
opendors/rules/split.py
opendors/rules/urls.py
opendors/rules/vcs.py
opendors-0.1.dev22.dist-info/LICENSES/CC-BY-4.0.txt
opendors-0.1.dev22.dist-info/LICENSES/CC0-1.0.txt
opendors-0.1.dev22.dist-info/LICENSES/MIT.txt
opendors-0.1.dev22.dist-info/METADATA
opendors-0.1.dev22.dist-info/WHEEL
opendors-0.1.dev22.dist-info/entry_points.txt
opendors-0.1.dev22.dist-info/RECORD
