Metadata-Version: 2.3
Name: opendors
Version: 0.1.dev22
Summary: Library for creating and interacting with OpenDORS datasets.
License: MIT
Author: Stephan Druskat
Author-email: stephan.druskat@dlr.de
Maintainer: Stephan Druskat
Maintainer-email: stephan.druskat@dlr.de
Requires-Python: >=3.11,<4.0
Classifier: Development Status :: 3 - Alpha
Requires-Dist: gitpython (>=3.1.44,<4.0.0)
Requires-Dist: jsonpath-ng (>=1.7.0,<2.0.0)
Requires-Dist: pydantic (>=2.10.6,<3.0.0)
Requires-Dist: ratelimit (>=2.2.1,<3.0.0)
Requires-Dist: requests (>=2.32.3,<3.0.0)
Requires-Dist: svine (>=0.2.1,<0.3.0)
Requires-Dist: urllib3 (>=2.3.0,<3.0.0)
